pydefinition/__init__.py
pydefinition/env_var.py
pydefinition/name_utilities.py
pydefinition-1.0.1.dist-info/METADATA
pydefinition-1.0.1.dist-info/WHEEL
pydefinition-1.0.1.dist-info/top_level.txt
pydefinition-1.0.1.dist-info/RECORD
