Metadata-Version: 2.4
Name: pydefinition
Version: 1.0.1
Summary: Environment-driven configuration helpers with low boilerplate
Author-email: PyDefinition Contributors <example@example.com>
License: MIT
Project-URL: Homepage, https://github.com/Rushberg/PyDefinition
Project-URL: Documentation, https://github.com/Rushberg/PyDefinition#readme
Project-URL: Issues, https://github.com/Rushberg/PyDefinition/issues
Project-URL: Changelog, https://github.com/Rushberg/PyDefinition/blob/main/CHANGELOG.md
Keywords: environment,configuration,env,variables,settings
Classifier: Development Status :: 4 - Beta
Classifier: Intended Audience :: Developers
Classifier: Programming Language :: Python :: 3
Classifier: Programming Language :: Python :: 3.6
Classifier: Programming Language :: Python :: 3.7
Classifier: Programming Language :: Python :: 3.8
Classifier: Programming Language :: Python :: 3.9
Classifier: Programming Language :: Python :: 3.10
Classifier: Programming Language :: Python :: 3.11
Classifier: License :: OSI Approved :: MIT License
Classifier: Operating System :: OS Independent
Classifier: Topic :: Software Development :: Libraries :: Python Modules
Requires-Python: >=3.6
Requires-Dist: typing-extensions>=4.0.0; python_version < "3.8"
